aniemore/__init__.py
aniemore/custom/__init__.py
aniemore/custom/modeling_classificators.py
aniemore/custom/modeling_hubert.py
aniemore/custom/modeling_unispeech_sat.py
aniemore/custom/modeling_wav2vec2.py
aniemore/custom/modeling_wavlm.py
aniemore/datasets.py
aniemore/models.py
aniemore/recognizers/__init__.py
aniemore/recognizers/multimodal.py
aniemore/recognizers/text.py
aniemore/recognizers/voice.py
aniemore/utils/__init__.py
aniemore/utils/classes.py
aniemore/utils/speech2text.py
aniemore-1.2.2.dist-info/LICENSE
aniemore-1.2.2.dist-info/METADATA
aniemore-1.2.2.dist-info/WHEEL
aniemore-1.2.2.dist-info/RECORD
