Metadata-Version: 2.1
Name: aniemore
Version: 1.2.2
Summary: Aniemore (Artem Nikita Ilya EMOtion REcognition) is a library for emotion recognition in voice and text for russian language.
License: MIT
Author: Ilya Lubenets
Author-email: lii291001@gmail.com
Maintainer: Ilya Lubenets
Maintainer-email: lii291001@gmail.com
Requires-Python: >=3.8,<3.12
Classifier: Development Status :: 5 - Production/Stable
Classifier: Environment :: GPU :: NVIDIA CUDA
Classifier: Intended Audience :: Developers
Classifier: Intended Audience :: Science/Research
Classifier: License :: OSI Approved :: MIT License
Classifier: Natural Language :: Russian
Classifier: Operating System :: OS Independent
Classifier: Programming Language :: Python :: 3
Classifier: Programming Language :: Python :: 3.8
Classifier: Programming Language :: Python :: 3.9
Classifier: Programming Language :: Python :: 3.10
Classifier: Programming Language :: Python :: 3.11
Classifier: Programming Language :: Python :: 3
Classifier: Topic :: Multimedia :: Sound/Audio :: Analysis
Classifier: Topic :: Multimedia :: Sound/Audio :: Speech
Classifier: Topic :: Scientific/Engineering :: Artificial Intelligence
Classifier: Topic :: Scientific/Engineering :: Information Analysis
Classifier: Topic :: Software Development :: Libraries :: Python Modules
Classifier: Topic :: Text Processing :: Linguistic
Requires-Dist: datasets (>=2.9.0,<3.0.0)
Requires-Dist: ffmpeg-python (>=0.2.0,<0.3.0)
Requires-Dist: numpy (>=1.24.2,<2.0.0)
Requires-Dist: openai-whisper (>=20230124,<20230125)
Requires-Dist: pip (>=23.0.1,<24.0.0)
Requires-Dist: setuptools (>=67.5.1,<68.0.0)
Requires-Dist: soundfile (>=0.12.1,<0.13.0) ; sys_platform == "win32"
Requires-Dist: sox (>=1.4.1,<2.0.0) ; sys_platform == "darwin"
Requires-Dist: sox (>=1.4.1,<2.0.0) ; sys_platform == "linux"
Requires-Dist: torch (>=2.0.0,<3.0.0)
Requires-Dist: torchaudio (>=2.0.1,<3.0.0)
Requires-Dist: transformers (>=4.26.1,<5.0.0)
Requires-Dist: typing-extensions (>=4.5.0,<5.0.0)
Requires-Dist: wheel (>=0.38.4,<0.39.0)
Project-URL: Bug Tracker, https://github.com/aniemore/Aniemore/issues
Project-URL: Hugging Face Homepage, https://huggingface.co/Aniemore
Project-URL: Repository, https://github.com/aniemore/Aniemore
